odoo9_addon_website_certificate-9.0.1.0.1-py2.7-nspkg.pth
odoo_addons/website_certificate/__openerp__.py
odoo_addons/website_certificate/certificate_view.xml
odoo_addons/website_certificate/__init__.py
odoo_addons/website_certificate/README.rst
odoo_addons/website_certificate/certificate.py
odoo9_addon_website_certificate-9.0.1.0.1.dist-info/top_level.txt
odoo9_addon_website_certificate-9.0.1.0.1.dist-info/WHEEL
odoo9_addon_website_certificate-9.0.1.0.1.dist-info/RECORD
odoo9_addon_website_certificate-9.0.1.0.1.dist-info/metadata.json
odoo9_addon_website_certificate-9.0.1.0.1.dist-info/DESCRIPTION.rst
odoo9_addon_website_certificate-9.0.1.0.1.dist-info/METADATA
odoo9_addon_website_certificate-9.0.1.0.1.dist-info/namespace_packages.txt
